queryguard/__init__.py
queryguard/analysis.py
queryguard/client.py
queryguard/console_utils.py
queryguard/main.py
queryguard_cli-0.2.0.dist-info/METADATA
queryguard_cli-0.2.0.dist-info/WHEEL
queryguard_cli-0.2.0.dist-info/entry_points.txt
queryguard_cli-0.2.0.dist-info/licenses/LICENSE
queryguard_cli-0.2.0.dist-info/RECORD
