Metadata-Version: 2.4
Name: queryguard-cli
Version: 0.2.0
Summary: A BigQuery Cost Analysis CLI Tool
License-File: LICENSE
Keywords: bigquery,gcp,cost-optimization,finops,cli
Author: Mark de Haan
Author-email: markdehaan90@gmail.com
Requires-Python: >=3.12,<4.0
Classifier: Intended Audience :: Developers
Classifier: Intended Audience :: System Administrators
Classifier: Operating System :: OS Independent
Classifier: Programming Language :: Python :: 3
Classifier: Programming Language :: Python :: 3.12
Classifier: Programming Language :: Python :: 3.13
Classifier: Programming Language :: Python :: 3.14
Classifier: Topic :: Database
Classifier: Topic :: Utilities
Requires-Dist: db-dtypes (>=1.2.0,<2.0.0)
Requires-Dist: google-cloud-bigquery (>=3.40.0,<4.0.0)
Requires-Dist: rich (>=14.2.0,<15.0.0)
Requires-Dist: typer (>=0.21.1,<0.22.0)
Project-URL: Repository, https://github.com/mark-de-haan/query-guard-cli
